LICENSE
MANIFEST.in
README.rst
setup.py
examples/arbiter1.spc
examples/arbiter10.spc
examples/arbiter15.spc
examples/arbiter20.spc
examples/arbiter3.spc
examples/arbiter5.spc
examples/gridworld_env.spc
gr1py/__init__.py
gr1py/_version.py
gr1py/cli.py
gr1py/minnx.py
gr1py/output.py
gr1py/solve.py
gr1py/tstruct.py
gr1py.egg-info/PKG-INFO
gr1py.egg-info/SOURCES.txt
gr1py.egg-info/dependency_links.txt
gr1py.egg-info/entry_points.txt
gr1py.egg-info/requires.txt
gr1py.egg-info/top_level.txt
gr1py/form/__init__.py
gr1py/form/gr1c.py
gr1py/form/parsetab.py
gr1py/form/util.py
tests/test_cli.py
tests/test_minnx.py
tests/test_realizability.py